snakelog/__init__.py
snakelog/common.py
snakelog/litelog.py
snakelog/souffle.py
snakelog/z3lite.py
snakelog-0.1.0.dist-info/WHEEL
snakelog-0.1.0.dist-info/METADATA
snakelog-0.1.0.dist-info/RECORD
