Metadata-Version: 2.1
Name: snakelog
Version: 0.1.0
Summary: 
Author: Philip Zucker
Author-email: philzook58@gmail.com
Requires-Python: >=3.8,<4.0
Classifier: Programming Language :: Python :: 3
Classifier: Programming Language :: Python :: 3.8
Classifier: Programming Language :: Python :: 3.9
Classifier: Programming Language :: Python :: 3.10
Classifier: Programming Language :: Python :: 3.11
Requires-Dist: networkx (>=2.8.7,<3.0.0)
